smdg/__init__.py
smdg/__main__.py
smdg/commandline.py
smdg/elements.py
smdg/html_generator.py
smdg/py.typed
smdg/strings.py
smdg-0.2.1.dist-info/LICENSE
smdg-0.2.1.dist-info/METADATA
smdg-0.2.1.dist-info/WHEEL
smdg-0.2.1.dist-info/top_level.txt
smdg-0.2.1.dist-info/RECORD
