Metadata-Version: 2.1
Name: smdg
Version: 0.2.1
Summary: Simple (pythonic) MarkDown Generator
Author-email: Rainer Schwarzbach <rainer@blackstream.de>
License: MIT License
Project-URL: Homepage, https://gitlab.com/blackstream-x/smdg
Project-URL: Documentation, https://blackstream-x.gitlab.io/smdg
Project-URL: CI, https://gitlab.com/blackstream-x/smdg/-/pipelines
Project-URL: Bug Tracker, https://gitlab.com/blackstream-x/smdg/-/issues
Project-URL: Repository, https://gitlab.com/blackstream-x/smdg.git
Keywords: markdown,generator
Classifier: Development Status :: 4 - Beta
Classifier: License :: OSI Approved :: MIT License
Classifier: Operating System :: OS Independent
Classifier: Programming Language :: Python :: 3
Classifier: Programming Language :: Python :: 3.9
Classifier: Programming Language :: Python :: 3.10
Classifier: Programming Language :: Python :: 3.11
Classifier: Programming Language :: Python :: 3.12
Classifier: Programming Language :: Python :: 3.13
Classifier: Programming Language :: Python :: 3 :: Only
Classifier: Intended Audience :: Developers
Classifier: Topic :: Software Development :: Libraries
Classifier: Topic :: Text Processing :: Markup :: Markdown
Classifier: Topic :: Utilities
Classifier: Typing :: Typed
Requires-Python: >=3.9
License-File: LICENSE
